MANIFEST.in
README
requirements.txt
setup.py
ajenti.plugin.ace.egg-info/PKG-INFO
ajenti.plugin.ace.egg-info/SOURCES.txt
ajenti.plugin.ace.egg-info/dependency_links.txt
ajenti.plugin.ace.egg-info/requires.txt
ajenti.plugin.ace.egg-info/top_level.txt
ajenti_plugin_ace/README.md
ajenti_plugin_ace/__init__.py
ajenti_plugin_ace/bower.json
ajenti_plugin_ace/plugin.yml
ajenti_plugin_ace/requirements.txt
ajenti_plugin_ace/locale/app.pot
ajenti_plugin_ace/locale/af/LC_MESSAGES/app.js
ajenti_plugin_ace/locale/af/LC_MESSAGES/app.po
ajenti_plugin_ace/locale/af/LC_MESSAGES/app.po~
ajenti_plugin_ace/locale/ar/LC_MESSAGES/app.js
ajenti_plugin_ace/locale/ar/LC_MESSAGES/app.po
ajenti_plugin_ace/locale/ar/LC_MESSAGES/app.po~
ajenti_plugin_ace/locale/be/LC_MESSAGES/app.js
ajenti_plugin_ace/locale/be/LC_MESSAGES/app.po
ajenti_plugin_ace/locale/be/LC_MESSAGES/app.po~
ajenti_plugin_ace/locale/bg/LC_MESSAGES/app.js
ajenti_plugin_ace/locale/bg/LC_MESSAGES/app.po
ajenti_plugin_ace/locale/bg/LC_MESSAGES/app.po~
ajenti_plugin_ace/locale/bn/LC_MESSAGES/app.js
ajenti_plugin_ace/locale/bn/LC_MESSAGES/app.po
ajenti_plugin_ace/locale/bn/LC_MESSAGES/app.po~
ajenti_plugin_ace/locale/bs/LC_MESSAGES/app.js
ajenti_plugin_ace/locale/bs/LC_MESSAGES/app.po
ajenti_plugin_ace/locale/ca/LC_MESSAGES/app.js
ajenti_plugin_ace/locale/ca/LC_MESSAGES/app.po
ajenti_plugin_ace/locale/ca/LC_MESSAGES/app.po~
ajenti_plugin_ace/locale/cs/LC_MESSAGES/app.js
ajenti_plugin_ace/locale/cs/LC_MESSAGES/app.po
ajenti_plugin_ace/locale/cs/LC_MESSAGES/app.po~
ajenti_plugin_ace/locale/da/LC_MESSAGES/app.js
ajenti_plugin_ace/locale/da/LC_MESSAGES/app.po
ajenti_plugin_ace/locale/da/LC_MESSAGES/app.po~
ajenti_plugin_ace/locale/de/LC_MESSAGES/app.js
ajenti_plugin_ace/locale/de/LC_MESSAGES/app.po
ajenti_plugin_ace/locale/de/LC_MESSAGES/app.po~
ajenti_plugin_ace/locale/el/LC_MESSAGES/app.js
ajenti_plugin_ace/locale/el/LC_MESSAGES/app.po
ajenti_plugin_ace/locale/el/LC_MESSAGES/app.po~
ajenti_plugin_ace/locale/en/LC_MESSAGES/app.po
ajenti_plugin_ace/locale/eo/LC_MESSAGES/app.js
ajenti_plugin_ace/locale/eo/LC_MESSAGES/app.po
ajenti_plugin_ace/locale/eo/LC_MESSAGES/app.po~
ajenti_plugin_ace/locale/es-ES/LC_MESSAGES/app.js
