Metadata-Version: 1.2
Name: ajenti.plugin.ace
Version: 0.32
Summary: Ace editor
Home-page: https://ajenti.org
Author: Ajenti project
Author-email: e@ajenti.org
License: UNKNOWN
Platform: UNKNOWN
Requires-Python: >=3
